dishookr/__init__.py
dishookr/app.py
dishookr/entry.py
dishookr/exceptions.py
dishookr/objects/allowed_mentions.py
dishookr/objects/component.py
dishookr/objects/embed.py
dishookr/objects/emoji.py
dishookr/objects/enums.py
dishookr/objects/interaction.py
dishookr/objects/interaction_callback.py
dishookr/objects/interaction_response.py
dishookr/objects/poll.py
dishookr/objects/user.py
dishookr/objects/webhook.py
dishookr-0.1.1.dist-info/LICENSE
dishookr-0.1.1.dist-info/METADATA
dishookr-0.1.1.dist-info/WHEEL
dishookr-0.1.1.dist-info/RECORD
